antnode-0.3.8.dist-info/METADATA
antnode-0.3.8.dist-info/WHEEL
antnode.libs/libgcc_s-5b5488a6.so.1
antnode/README.md
antnode/__init__.py
antnode/_antnode.abi3.so
antnode-0.3.8.dist-info/RECORD
