Metadata-Version: 2.4
Name: antnode
Version: 0.3.8
Requires-Dist: maturin>=1.7.4
Requires-Dist: pip>=24.3.1
Summary: The Autonomi node binary
Home-Page: https://maidsafe.net
Author: MaidSafe Developers <dev@maidsafe.net>
Author-email: MaidSafe Developers <dev@maidsafe.net>
License: GPL-3.0
Requires-Python: >=3.8
Project-URL: Source Code, https://github.com/maidsafe/autonomi
